example_b_pythonPete/__init__.py
example_b_pythonPete/demo_b.py
example_b_pythonpete-0.0.1.dist-info/METADATA
example_b_pythonpete-0.0.1.dist-info/WHEEL
example_b_pythonpete-0.0.1.dist-info/licenses/LICENSE
example_b_pythonpete-0.0.1.dist-info/RECORD
